src/__init__.py
src/githubapi.py
buildbot_githubapi-0.1.2.dist-info/METADATA
buildbot_githubapi-0.1.2.dist-info/WHEEL
buildbot_githubapi-0.1.2.dist-info/entry_points.txt
buildbot_githubapi-0.1.2.dist-info/top_level.txt
buildbot_githubapi-0.1.2.dist-info/RECORD
